api_connecter_mcp/__init__.py
api_connecter_mcp/main.py
api_connecter_mcp/server.py
api_connecter_mcp/config/__init__.py
api_connecter_mcp/config/api_config_manager.py
api_connecter_mcp/config/api_connector.py
api_connecter_mcp/config/api_data_storage.py
api_connecter_mcp/core/__init__.py
api_connecter_mcp/core/api_manager.py
api_connecter_mcp/utils/__init__.py
api_connecter_mcp/utils/data_transformer.py
api_connecter_mcp-1.0.1.dist-info/METADATA
api_connecter_mcp-1.0.1.dist-info/WHEEL
api_connecter_mcp-1.0.1.dist-info/entry_points.txt
api_connecter_mcp-1.0.1.dist-info/top_level.txt
api_connecter_mcp-1.0.1.dist-info/RECORD
