Metadata-Version: 2.4
Name: api-connecter-mcp
Version: 1.0.1
Summary: Universal API Connector MCP for AI applications
Author-email: szqshan <szqshan@example.com>
License: MIT
Project-URL: Homepage, https://github.com/szqshan/api-connecter-mcp
Project-URL: Bug Reports, https://github.com/szqshan/api-connecter-mcp/issues
Project-URL: Source, https://github.com/szqshan/api-connecter-mcp
Keywords: mcp,api,connector,ai,http,rest
Classifier: Development Status :: 4 - Beta
Classifier: Intended Audience :: Developers
Classifier: License :: OSI Approved :: MIT License
Classifier: Programming Language :: Python :: 3
Classifier: Programming Language :: Python :: 3.8
Classifier: Programming Language :: Python :: 3.9
Classifier: Programming Language :: Python :: 3.10
Classifier: Programming Language :: Python :: 3.11
Classifier: Programming Language :: Python :: 3.12
Classifier: Topic :: Software Development :: Libraries :: Python Modules
Classifier: Topic :: Internet :: WWW/HTTP :: HTTP Servers
Classifier: Topic :: Scientific/Engineering :: Artificial Intelligence
Requires-Python: >=3.8
Requires-Dist: mcp>=1.2.0
Requires-Dist: requests>=2.31.0
Requires-Dist: httpx>=0.24.0
Requires-Dist: pydantic>=2.0.0
Requires-Dist: pyyaml>=6.0
Requires-Dist: python-dotenv>=1.0.0
Requires-Dist: python-dateutil>=2.8.0
